github2pandas_manager/__init__.py
github2pandas_manager/__main__.py
github2pandas_manager/config_parser.py
github2pandas_manager/data_extractor.py
github2pandas_manager/data_merger.py
github2pandas_manager/repository_handler.py
github2pandas_manager/utilities.py
github2pandas_manager-0.0.9.dist-info/LICENSE
github2pandas_manager-0.0.9.dist-info/METADATA
github2pandas_manager-0.0.9.dist-info/WHEEL
github2pandas_manager-0.0.9.dist-info/top_level.txt
github2pandas_manager-0.0.9.dist-info/RECORD
