Metadata-Version: 2.1
Name: github2pandas-manager
Version: 0.0.9
Summary: Aggregation of github activities on multiple repositories based on github2pandas
Home-page: https://github.com/TUBAF-IFI-DiPiT/github2pandas_manager
Author: Sebastian Zug, Mezekr Weldu, Galina Rudolf
License: BSD 2
Download-URL: https://github.com/user/reponame/archive/v_01.tar.gz
Keywords: git,github,git mining,learning analytics
Platform: UNKNOWN
Classifier: Programming Language :: Python :: 3
Classifier: Operating System :: OS Independent
Requires-Python: >=3.8
License-File: LICENSE
Requires-Dist: github2pandas
